README
setup.py
bin/peafowl
peafowl/__init__.py
peafowl/collection.py
peafowl/handler.py
peafowl/peafowl.py
peafowl/queue.py
peafowl/runner.py
peafowl/server.py
peafowl/utils.py
peafowl.egg-info/PKG-INFO
peafowl.egg-info/SOURCES.txt
peafowl.egg-info/dependency_links.txt
peafowl.egg-info/top_level.txt