Metadata-Version: 1.0
Name: peafowl
Version: 0.9
Summary: A light weight server for reliable distributed message passing.
Home-page: http://wiki.github.com/cyberdelia/peafowl
Author: Timothee Peignier
Author-email: tim@tryphon.org
License: BSD License
Keywords: peafowl queue messaging distributed memcache starling
Platform: Unix
Classifier: Development Status :: 4 - Beta
Classifier: License :: OSI Approved :: BSD License
Classifier: Operating System :: Unix
Classifier: Programming Language :: Python
